seekr/__init__.py
seekr/__version__.py
seekr/adj_pval.py
seekr/console_scripts.py
seekr/fasta.py
seekr/fasta_reader.py
seekr/filter_gencode.py
seekr/find_dist.py
seekr/find_pval.py
seekr/kmer_comp_textplot.py
seekr/kmer_count_barplot.py
seekr/kmer_counts.py
seekr/kmer_dendrogram.py
seekr/kmer_heatmap.py
seekr/kmer_indi_textplot.py
seekr/kmer_leiden.py
seekr/kmer_msd_barplot.py
seekr/my_tqdm.py
seekr/pearson.py
seekr/data/arial.ttf
seekr/data/gencode.vM25.lncRNA_transcripts.unique.genesequence_withfullairn.fa
seekr-2.0.2.dist-info/LICENSE
seekr-2.0.2.dist-info/METADATA
seekr-2.0.2.dist-info/WHEEL
seekr-2.0.2.dist-info/entry_points.txt
seekr-2.0.2.dist-info/top_level.txt
seekr-2.0.2.dist-info/RECORD
