Metadata-Version: 2.1
Name: seekr
Version: 2.0.2
Summary: Count small kmer frequencies in nucleotide sequences.
Home-page: https://github.com/CalabreseLab/seekr
Author: Jessime Kirk, Shuang Li, Luke Ni
Author-email: shuang9@email.unc.edu
License: MIT
Classifier: Intended Audience :: Science/Research
Classifier: License :: OSI Approved :: MIT License
Classifier: Natural Language :: English
Classifier: Programming Language :: Python :: 3.9
Requires-Python: >=3.9
License-File: LICENSE
Requires-Dist: cython
Requires-Dist: tqdm
Requires-Dist: numpy
Requires-Dist: pandas
Requires-Dist: requests
Requires-Dist: networkx >=3.1
Requires-Dist: python-igraph ==0.10.4
Requires-Dist: leidenalg ==0.9.1
Requires-Dist: matplotlib >=3.7
Requires-Dist: seaborn
Requires-Dist: scipy
Requires-Dist: statsmodels
